ExoPix/__init__.py
ExoPix-0.1.0.dist-info/METADATA
ExoPix-0.1.0.dist-info/WHEEL
ExoPix-0.1.0.dist-info/top_level.txt
ExoPix-0.1.0.dist-info/RECORD
