Metadata-Version: 2.1
Name: ExoPix
Version: 0.1.0
Summary: ExoPix: Applying PSF Subtraction with pyKLIP to JWST
Home-page: https://github.com/jeaadams/ExoPix.git
Author: Jea Adams, Jason Wang
Author-email: jadams21@amherst.edu
License: UNKNOWN
Keywords: KLIP PSF Subtraction Exoplanets Astronomy JWST
Platform: UNKNOWN
Classifier: Intended Audience :: Science/Research
Classifier: Topic :: Scientific/Engineering :: Astronomy
Classifier: Programming Language :: Python :: 3.8
Requires-Dist: numpy
Requires-Dist: scipy
Requires-Dist: pyklip
Requires-Dist: astropy
Requires-Dist: matplotlib
Requires-Dist: emcee
Requires-Dist: corner
Requires-Dist: nbsphinx
